[
  {
    "image": "Bowls001.jpg",
    "thumbnail": "ThumbBowls001.jpg",
    "shortDescription": "Bowl 001",
    "newRow": true
  },
  {
    "image": "Bowls002.jpg",
    "thumbnail": "ThumbBowls002.jpg",
    "shortDescription": "Bowl 002",
    "newRow": true
  },
  {
    "image": "Bowls003.jpg",
    "thumbnail": "ThumbBowls003.jpg",
    "shortDescription": "Bowl 003",
    "newRow": true
  },
  {
    "image": "Bowls004.jpg",
    "thumbnail": "ThumbBowls004.jpg",
    "shortDescription": "Bowl 004",
    "newRow": false
  },
  {
    "image": "Bowls005.jpg",
    "thumbnail": "ThumbBowls005.jpg",
    "shortDescription": "Bowl 005",
    "newRow": false
  },
  {
    "image": "Bowls009.jpg",
    "thumbnail": "ThumbBowls009.jpg",
    "shortDescription": "Bowl 009",
    "newRow": true
  },
  {
    "image": "Bowls006.jpg",
    "thumbnail": "ThumbBowls006.jpg",
    "shortDescription": "Bowl 006",
    "newRow": true
  },
  {
    "image": "Bowls007.jpg",
    "thumbnail": "ThumbBowls007.jpg",
    "shortDescription": "Bowl 007",
    "newRow": false
  },
  {
    "image": "Bowls008.jpg",
    "thumbnail": "ThumbBowls008.jpg",
    "shortDescription": "Bowl 008",
    "newRow": false
  },
  {
    "image": "Bowls010.jpg",
    "thumbnail": "ThumbBowls010.jpg",
    "shortDescription": "Bowl 010",
    "newRow": true
  },
  {
    "image": "Bowls011.jpg",
    "thumbnail": "ThumbBowls011.jpg",
    "shortDescription": "Bowl 011",
    "newRow": true
  },
  {
    "image": "Bowls012.jpg",
    "thumbnail": "ThumbBowls012.jpg",
    "shortDescription": "Bowl 012",
    "newRow": false
  },
  {
    "image": "Bowls013.jpg",
    "thumbnail": "ThumbBowls013.jpg",
    "shortDescription": "Bowl 013",
    "newRow": false
  },
  {
    "image": "Bowls014.jpg",
    "thumbnail": "ThumbBowls014.jpg",
    "shortDescription": "Bowl 014",
    "newRow": true
  },
  {
    "image": "Bowls015.jpg",
    "thumbnail": "ThumbBowls015.jpg",
    "shortDescription": "Bowl 015",
    "newRow": true
  },
  {
    "image": "Bowls016.jpg",
    "thumbnail": "ThumbBowls016.jpg",
    "shortDescription": "Bowl 016",
    "newRow": false
  },
  {
    "image": "Bowls017.jpg",
    "thumbnail": "ThumbBowls017.jpg",
    "shortDescription": "Bowl 017",
    "newRow": false
  },
  {
    "image": "Bowls018.jpg",
    "thumbnail": "ThumbBowls018.jpg",
    "shortDescription": "Bowl 018",
    "newRow": true
  },
  {
    "image": "Bowls019.jpg",
    "thumbnail": "ThumbBowls019.jpg",
    "shortDescription": "Bowl 019",
    "newRow": false
  },
  {
    "image": "Bowls020.jpg",
    "thumbnail": "ThumbBowls020.jpg",
    "shortDescription": "Bowl 020",
    "newRow": true
  },
  {
    "image": "Bowls021.jpg",
    "thumbnail": "ThumbBowls021.jpg",
    "shortDescription": "Bowl 021",
    "newRow": true
  },
  {
    "image": "Bowls022.jpg",
    "thumbnail": "ThumbBowls022.jpg",
    "shortDescription": "Bowl 022",
    "newRow": false
  },
  {
    "image": "Bowls023.jpg",
    "thumbnail": "ThumbBowls023.jpg",
    "shortDescription": "Bowl 023",
    "newRow": true
  },
  {
    "image": "Bowls024.jpg",
    "thumbnail": "ThumbBowls024.jpg",
    "shortDescription": "Bowl 024",
    "newRow": true
  },
  {
    "image": "Bowls025.jpg",
    "thumbnail": "ThumbBowls025.jpg",
    "shortDescription": "Bowl 025",
    "newRow": false
  },
  {
    "image": "Bowls026.jpg",
    "thumbnail": "ThumbBowls026.jpg",
    "shortDescription": "Bowl 026",
    "newRow": true
  },
  {
    "image": "Bowls027.jpg",
    "thumbnail": "ThumbBowls027.jpg",
    "shortDescription": "Bowl 027",
    "newRow": false
  },
  {
    "image": "Bowls028.jpg",
    "thumbnail": "ThumbBowls028.jpg",
    "shortDescription": "Bowl 028",
    "newRow": false
  },
  {
    "image": "Bowls029.jpg",
    "thumbnail": "ThumbBowls029.jpg",
    "shortDescription": "Bowl 029",
    "newRow": true
  },
  {
    "image": "Bowls030.jpg",
    "thumbnail": "ThumbBowls030.jpg",
    "shortDescription": "Bowl 030",
    "newRow": false
  },
  {
    "image": "Bowls031.jpg",
    "thumbnail": "ThumbBowls031.jpg",
    "shortDescription": "Bowl 031",
    "newRow": false
  },
  {
    "image": "Bowls032.jpg",
    "thumbnail": "ThumbBowls032.jpg",
    "shortDescription": "Bowl 032",
    "newRow": false
  },
  {
    "image": "Bowls033.jpg",
    "thumbnail": "ThumbBowls033.jpg",
    "shortDescription": "Bowl 033",
    "newRow": true
  },
  {
    "image": "Bowls034.jpg",
    "thumbnail": "ThumbBowls034.jpg",
    "shortDescription": "Bowl 034",
    "newRow": false
  },
  {
    "image": "Bowls035.jpg",
    "thumbnail": "ThumbBowls035.jpg",
    "shortDescription": "Bowl 035",
    "newRow": true
  },
  {
    "image": "Bowls036.jpg",
    "thumbnail": "ThumbBowls036.jpg",
    "shortDescription": "Bowl 036",
    "newRow": false
  },
  {
    "image": "Bowls037.jpg",
    "thumbnail": "ThumbBowls037.jpg",
    "shortDescription": "Bowl 037",
    "newRow": true
  },
  {
    "image": "Bowls038.jpg",
    "thumbnail": "ThumbBowls038.jpg",
    "shortDescription": "Bowl 038",
    "newRow": true
  },
  {
    "image": "Bowls039.jpg",
    "thumbnail": "ThumbBowls039.jpg",
    "shortDescription": "Bowl 039",
    "newRow": false
  },
  {
    "image": "Bowls040.jpg",
    "thumbnail": "ThumbBowls040.jpg",
    "shortDescription": "Bowl 040",
    "newRow": false
  },
  {
    "image": "Bowls041.jpg",
    "thumbnail": "ThumbBowls041.jpg",
    "shortDescription": "Bowl 041",
    "newRow": true
  },
  {
    "image": "Bowls042.jpg",
    "thumbnail": "ThumbBowls042.jpg",
    "shortDescription": "Bowl 042",
    "newRow": false
  },
  {
    "image": "Bowls043.jpg",
    "thumbnail": "ThumbBowls043.jpg",
    "shortDescription": "Bowl 043",
    "newRow": false
  },
  {
    "image": "Bowls044.jpg",
    "thumbnail": "ThumbBowls044.jpg",
    "shortDescription": "Bowl 044",
    "newRow": true
  },
  {
    "image": "Bowls045.jpg",
    "thumbnail": "ThumbBowls045.jpg",
    "shortDescription": "Bowl 045",
    "newRow": false
  },
  {
    "image": "Bowls046.jpg",
    "thumbnail": "ThumbBowls046.jpg",
    "shortDescription": "Bowl 046",
    "newRow": true
  },
  {
    "image": "Bowls047.jpg",
    "thumbnail": "ThumbBowls047.jpg",
    "shortDescription": "Bowl 047",
    "newRow": false
  },
  {
    "image": "Bowls048.jpg",
    "thumbnail": "ThumbBowls048.jpg",
    "shortDescription": "Bowl 048",
    "newRow": false
  },
  {
    "image": "Bowls049.jpg",
    "thumbnail": "ThumbBowls049.jpg",
    "shortDescription": "Bowl 049",
    "newRow": false
  }
]